LICENSE
README.md
setup.py
cron_monitor/__init__.py
cron_monitor/constants.py
cron_monitor/cron_monitor_sdk.py
cron_monitor/decorator.py
cron_monitor/http_client.py
cron_monitor/initialiser.py
cron_monitor/logger.py
starecase_cron_monitor.egg-info/PKG-INFO
starecase_cron_monitor.egg-info/SOURCES.txt
starecase_cron_monitor.egg-info/dependency_links.txt
starecase_cron_monitor.egg-info/requires.txt
starecase_cron_monitor.egg-info/top_level.txt
tests/__init__.py
tests/test_http_client.py