Metadata-Version: 2.1
Name: starecase-cron-monitor
Version: 0.1.3
Summary: This is a Python package designed for monitoring cron jobs through Starecase.io
Home-page: https://github.com/madhukaraman/starecase-cron-monitor
Author: Aman Madhukar
Author-email: madhukaraman02@gmail.com  
Classifier: Programming Language :: Python :: 3
Classifier: License :: OSI Approved :: MIT License
Classifier: Operating System :: OS Independent
Requires-Python: >=3.6
License-File: LICENSE
Requires-Dist: requests==2.32.2
